LICENSE
MANIFEST.in
README
setup.py
pydss/__init__.py
pydss.egg-info/PKG-INFO
pydss.egg-info/SOURCES.txt
pydss.egg-info/dependency_links.txt
pydss.egg-info/top_level.txt
pydss.egg-info/zip-safe
pydss/common/AutoAddImpl.py
pydss/common/CommandLineDSSForms.py
pydss/common/ControlProblem.py
pydss/common/ControlQueueImpl.py
pydss/common/DSSBus.py
pydss/common/DSSCallBacks.py
pydss/common/DSSCktElement.py
pydss/common/DSSClassDefs.py
pydss/common/DSSClassImpl.py
pydss/common/DSSClassesImpl.py
pydss/common/DSSGlobals.py
pydss/common/ExportResults.py
pydss/common/FeederImpl.py
pydss/common/FeederObjImpl.py
pydss/common/PowerTerminal.py
pydss/common/ShowResults.py
pydss/common/SolutionAlgs.py
pydss/common/SolutionImpl.py
pydss/common/SolutionObjImpl.py
pydss/common/YMatrix.py
pydss/common/__init__.py
pydss/control/CapControlImpl.py
pydss/control/CapControlObjImpl.py
pydss/control/ControlAction.py
pydss/control/ControlClassImpl.py
pydss/control/ControlElemImpl.py
pydss/control/GenDispatcherImpl.py
pydss/control/GenDispatcherObjImpl.py
pydss/control/RecloserImpl.py
pydss/control/RecloserObjImpl.py
pydss/control/RegControlImpl.py
pydss/control/RegControlObjImpl.py
pydss/control/RelayImpl.py
pydss/control/RelayObjImpl.py
pydss/control/StorageControllerImpl.py
pydss/control/StorageControllerObjImpl.py
pydss/control/SwtControlImpl.py
pydss/control/SwtControlObjImpl.py
pydss/control/__init__.py
pydss/conversion/EquivalentImpl.py
pydss/conversion/EquivalentObjImpl.py
pydss/conversion/GICLineImpl.py
pydss/conversion/GICLineObjImpl.py
pydss/conversion/GenUserModelImpl.py
pydss/conversion/GeneratorImpl.py
pydss/conversion/GeneratorObjImpl.py
pydss/conversion/ISourceImpl.py
pydss/conversion/ISourceObjImpl.py
pydss/conversion/LoadImpl.py
pydss/conversion/LoadObjImpl.py
pydss/conversion/PCClassImpl.py
pydss/conversion/PCElementImpl.py
pydss/conversion/PVSystemImpl.py
pydss/conversion/PVSystemObjImpl.py
pydss/conversion/PVSystemUserModelImpl.py
pydss/conversion/StorageImpl.py
pydss/conversion/StorageObjImpl.py
pydss/conversion/StoreUserModelImpl.py
pydss/conversion/VSourceImpl.py
pydss/conversion/VSourceObjImpl.py
