Metadata-Version: 1.0
Name: pydss
Version: 0.1a
Summary: Python Distribution System Simuator
Home-page: UNKNOWN
Author: Richard Lincoln
Author-email: r.w.lincoln@gmail.com
License: Apache License 2.0
Platform: UNKNOWN
